libgyronimo.0.2.dylib
libgyronimo.dylib
neatpp.cpython-38-darwin.so
neat/__init__.py
neat/util/NEAT_Mercier.py
neat/util/functions.py
neat/util/main.py
neat/util/plotting.py
neat/util/stell_repo.py
neatstel-0.0.1.dist-info/LICENSE
neatstel-0.0.1.dist-info/METADATA
neatstel-0.0.1.dist-info/WHEEL
neatstel-0.0.1.dist-info/top_level.txt
neatstel-0.0.1.dist-info/RECORD
